pyproject.toml
setup.cfg
setup.py
ocr/__init__.py
ocr/keywords/__init__.py
ocr/keywords/defaults.py
ocr/keywords/locator.py
ocr/pdf_converter/__init__.py
ocr/pdf_converter/converter.py
ocr_cv.egg-info/PKG-INFO
ocr_cv.egg-info/SOURCES.txt
ocr_cv.egg-info/dependency_links.txt
ocr_cv.egg-info/not-zip-safe
ocr_cv.egg-info/top_level.txt
src/__init__.py
src/main.py
src/test.py