Metadata-Version: 1.0
Name: ocr-cv
Version: 1.0.13
Summary: Generate keywords from CVs
Home-page: https://gitlab.com/galbh/ocr
Author: Gal Ben Haim
Author-email: galbhmusic@gmail.com
License: MIT
Platform: UNKNOWN
